dfp.py
dfp-0.9.1.dist-info/LICENSE
dfp-0.9.1.dist-info/METADATA
dfp-0.9.1.dist-info/WHEEL
dfp-0.9.1.dist-info/top_level.txt
dfp-0.9.1.dist-info/RECORD
