Metadata-Version: 2.1
Name: dfp
Version: 0.9.1
Summary: A suite of functional tools for all your functional programming
Home-page: https://github.com/jaypmorgan/dfp
Author: Jay Morgan
Author-email: jay@morganwastaken.com
Requires-Python: >=3.6
License-File: LICENSE
Requires-Dist: tqdm >=4.62
Requires-Dist: pandas ==1.*
